stor4build/__about__.py
stor4build/__init__.py
stor4build/__main__.py
stor4build/database.py
stor4build/dxcoil.py
stor4build/icetank.py
stor4build/osmeasures.py
stor4build/run.py
stor4build/schema.py
stor4build/system.py
stor4build/util.py
stor4build/api/__init__.py
stor4build/cli/__init__.py
stor4build/tessbed/__init__.py
stor4build-0.3.0.dist-info/METADATA
stor4build-0.3.0.dist-info/WHEEL
stor4build-0.3.0.dist-info/entry_points.txt
stor4build-0.3.0.dist-info/licenses/LICENSE.txt
stor4build-0.3.0.dist-info/RECORD
