Metadata-Version: 2.4
Name: stor4build
Version: 0.3.0
Summary: Stor4Build TES benefits and decision tool
Project-URL: Documentation, https://github.com/stor4build/stor4build#readme
Project-URL: Issues, https://github.com/stor4build/stor4build/issues
Project-URL: Source, https://github.com/stor4build/stor4build
Author: Eric Bonnema
Author-email: "Jason W. DeGraw" <jason.degraw@gmail.com>
License-Expression: BSD-3-Clause
License-File: LICENSE.txt
Classifier: Development Status :: 4 - Beta
Classifier: Programming Language :: Python
Classifier: Programming Language :: Python :: 3.8
Classifier: Programming Language :: Python :: 3.9
Classifier: Programming Language :: Python :: 3.10
Classifier: Programming Language :: Python :: 3.11
Classifier: Programming Language :: Python :: 3.12
Classifier: Programming Language :: Python :: 3.13
Classifier: Programming Language :: Python :: Implementation :: CPython
Classifier: Programming Language :: Python :: Implementation :: PyPy
Requires-Python: >=3.8
Requires-Dist: click
Requires-Dist: flask
Requires-Dist: marshmallow
Requires-Dist: pandas
Requires-Dist: psycopg2-binary
Requires-Dist: scipy
Requires-Dist: secondarycoolantprops
